pythonperlin/__init__.py
pythonperlin/perlin.py
pythonperlin-0.0.3.dist-info/LICENSE
pythonperlin-0.0.3.dist-info/METADATA
pythonperlin-0.0.3.dist-info/WHEEL
pythonperlin-0.0.3.dist-info/top_level.txt
pythonperlin-0.0.3.dist-info/RECORD
