Metadata-Version: 2.1
Name: pythonperlin
Version: 0.0.3
Summary: Perlin noise in python - seamlessly tile in any dimensions
Home-page: https://github.com/timpyrkov/pythonperlin
Author: Tim Pyrkov
Author-email: tim.pyrkov@gmail.com
License: MIT License
Platform: UNKNOWN
Classifier: Programming Language :: Python :: 3
Classifier: License :: OSI Approved :: MIT License
Classifier: Topic :: Artistic Software
Requires-Python: >=3.6
License-File: LICENSE
Requires-Dist: numpy
